README.md
monoplt.py
setup.py
monoplt.egg-info/PKG-INFO
monoplt.egg-info/SOURCES.txt
monoplt.egg-info/dependency_links.txt
monoplt.egg-info/top_level.txt